yosai/__init__.py
yosai/core/__init__.py
yosai/core/exceptions.py
yosai/core/account/__init__.py
yosai/core/account/abcs.py
yosai/core/account/account.py
yosai/core/authc/__init__.py
yosai/core/authc/abcs.py
yosai/core/authc/authc.py
yosai/core/authc/authc_settings.py
yosai/core/authc/credential.py
yosai/core/authc/strategy.py
yosai/core/authz/__init__.py
yosai/core/authz/abcs.py
yosai/core/authz/authz.py
yosai/core/cache/__init__.py
yosai/core/cache/abcs.py
yosai/core/concurrency/__init__.py
yosai/core/concurrency/concurrency.py
yosai/core/conf/__init__.py
yosai/core/conf/yosaisettings.py
yosai/core/event/__init__.py
yosai/core/event/abcs.py
yosai/core/event/event.py
yosai/core/logging/__init__.py
yosai/core/logging/formatters.py
yosai/core/logging/slogging.py
yosai/core/mgt/__init__.py
yosai/core/mgt/abcs.py
yosai/core/mgt/mgt.py
yosai/core/mgt/mgt_settings.py
yosai/core/realm/__init__.py
yosai/core/realm/abcs.py
yosai/core/realm/realm.py
yosai/core/serialize/__init__.py
yosai/core/serialize/abcs.py
yosai/core/serialize/marshalling.py
yosai/core/serialize/serialize.py
yosai/core/serialize/serializers/__init__.py
yosai/core/serialize/serializers/cbor.py
yosai/core/serialize/serializers/json.py
yosai/core/serialize/serializers/msgpack.py
yosai/core/session/__init__.py
yosai/core/session/abcs.py
yosai/core/session/session.py
yosai/core/session/session_settings.py
yosai/core/session/session_untested.py
yosai/core/subject/__init__.py
yosai/core/subject/abcs.py
yosai/core/subject/identifier.py
yosai/core/subject/subject.py
yosai/core/utils/__init__.py
yosai/core/utils/utils.py
yosai/web/__init__.py
yosai/web/exceptions.py
yosai/web/mgt/__init__.py
yosai/web/mgt/mgt.py
yosai/web/registry/__init__.py
yosai/web/registry/abcs.py
yosai/web/registry/registry_settings.py
yosai/web/session/__init__.py
yosai/web/session/session.py
yosai/web/subject/__init__.py
yosai/web/subject/abcs.py
yosai/web/subject/subject.py
yosai-0.3.2.dist-info/DESCRIPTION.rst
yosai-0.3.2.dist-info/METADATA
yosai-0.3.2.dist-info/RECORD
yosai-0.3.2.dist-info/WHEEL
yosai-0.3.2.dist-info/metadata.json
yosai-0.3.2.dist-info/top_level.txt
