Metadata-Version: 2.0
Name: yosai
Version: 0.3.2
Summary: Yosai is a powerful security framework with an intuitive api.
Home-page: http://yosaiproject.github.io/yosai
Author: Darin Gordon
Author-email: dkcdkg@gmail.com
License: Apache License 2.0
Keywords: security rbac session authentication authorization
Platform: UNKNOWN
Classifier: Development Status :: 4 - Beta
Classifier: Intended Audience :: Developers
Classifier: License :: OSI Approved :: Apache Software License
Classifier: Programming Language :: Python
Classifier: Programming Language :: Python :: 3
Classifier: Programming Language :: Python :: 3.4
Classifier: Programming Language :: Python :: 3.5
Classifier: Topic :: Security
Classifier: Topic :: Software Development :: Libraries :: Application Frameworks
Classifier: Topic :: Software Development :: Libraries :: Python Modules
Requires-Dist: PyYAML
Requires-Dist: python-dateutil
Requires-Dist: pytz
Requires-Dist: PyPubSub
Requires-Dist: argon2-cffi
Requires-Dist: bcrypt
Requires-Dist: passlib
Requires-Dist: cryptography
Requires-Dist: msgpack-python
Requires-Dist: cbor2
Requires-Dist: python-rapidjson
